solvent/__init__.py
solvent/__main__.py
solvent/cli.py
solvent/gui.py
solvent/scripts/__init__.py
solvent/scripts/gop.py
solvent/scripts/lindell.py
solvent/scripts/misc.py
solvent/scripts/nazi.py
solvent/scripts/sites/action.greene2020.com/stop-the-steal-rd/default.yml
solvent/scripts/sites/action.iowagunowners.org/action/re-open-iowa-for-business/default.yml
solvent/scripts/sites/action.iowagunowners.org/sign-up/default.yml
solvent/scripts/sites/apps.apple.com/us/app/truth-social/id1586018825/default.yml
solvent/scripts/sites/chiefjamescraig.com/@/default.yml
solvent/scripts/sites/ci.criticalimpact.com/wc/wc.cfm/default.yml
solvent/scripts/sites/defendyourballot.formstack.com/forms/voter_fraud/default.yml
solvent/scripts/sites/donjr.com/@/default.yml
solvent/scripts/sites/donjr.com/challenge/contact_form.yml
solvent/scripts/sites/donjr.com/checkouts/c/{c}/information/default.yml
solvent/scripts/sites/donjr.com/checkouts/c/{c}/payment/default.yml
solvent/scripts/sites/donjr.com/checkouts/c/{c}/shipping/default.yml
solvent/scripts/sites/donjr.com/collections/all/default.yml
solvent/scripts/sites/donjr.com/collections/all/products/{slug}/default.yml
solvent/scripts/sites/donjr.com/{product}/checkouts/{cart}/default.yml
solvent/scripts/sites/fa.ml.com/connecticut/stamford/theiannazzogroup/default.yml
solvent/scripts/sites/frankspeech.com/@/default.yml
solvent/scripts/sites/frankspeech.com/redirect.html/default.yml
solvent/scripts/sites/frankspeech.com/user/Signup/default.yml
solvent/scripts/sites/frankspeech.com/user/register/default.yml
solvent/scripts/sites/fs10.formsite.com/res/showFormEmbed/default.yml
solvent/scripts/sites/fs10.formsite.com/res/showSuccessPage/default.yml
solvent/scripts/sites/fs10.formsite.com/res/submit/default.yml
solvent/scripts/sites/fs21.formsite.com/res/showFormEmbed/default.yml
solvent/scripts/sites/fs21.formsite.com/res/showSuccessPage/default.yml
solvent/scripts/sites/fs21.formsite.com/res/submit/default.yml
solvent-25.3.7.dist-info/METADATA
solvent-25.3.7.dist-info/WHEEL
solvent-25.3.7.dist-info/entry_points.txt
solvent-25.3.7.dist-info/RECORD
