Metadata-Version: 2.3
Name: solvent
Version: 25.3.7
Summary: Kills off fake grass.
License: MIT
Author: Solvent
Author-email: solvent@example.com
Requires-Python: >=3.9,<4.0
Classifier: License :: OSI Approved :: MIT License
Classifier: Programming Language :: Python :: 3
Classifier: Programming Language :: Python :: 3.9
Classifier: Programming Language :: Python :: 3.10
Classifier: Programming Language :: Python :: 3.11
Classifier: Programming Language :: Python :: 3.12
Classifier: Programming Language :: Python :: 3.13
Requires-Dist: caffeine (>=0.5,<0.6) ; sys_platform == "darwin"
Requires-Dist: flet (>=0.25.2,<0.26.0)
Requires-Dist: pomace (>=0.12.11,<0.13.0)
Requires-Dist: typer (>=0.9,<0.10)
